cinematips/__init__.py
cinematips/imdbrating.py
cinematips/imdbrequest.py
cinematips/movie.py
cinematips/response.py
cinematips-0.1.0.dist-info/LICENSE
cinematips-0.1.0.dist-info/METADATA
cinematips-0.1.0.dist-info/WHEEL
cinematips-0.1.0.dist-info/top_level.txt
cinematips-0.1.0.dist-info/RECORD
