Metadata-Version: 2.1
Name: cinematips
Version: 0.1.0
Home-page: https://github.com/zakenobi/cinematips
Author: Zachary Gagnou & Alexandra Mille-Egea
License-File: LICENSE
Requires-Dist: requests (==2.28.1)
